Olxparsing.py
olxparsing-0.0.1.dist-info/WHEEL
olxparsing-0.0.1.dist-info/METADATA
olxparsing-0.0.1.dist-info/RECORD
