Metadata-Version: 2.1
Name: olxparsing
Version: 0.0.1
Summary: Olx parsing qilish
License: ^3.8
Author: Brodyaga
Requires-Python: >=3.8,<4.0
Classifier: License :: Other/Proprietary License
Classifier: Programming Language :: Python :: 3
Classifier: Programming Language :: Python :: 3.8
Classifier: Programming Language :: Python :: 3.9
Classifier: Programming Language :: Python :: 3.10
Classifier: Programming Language :: Python :: 3.11
